pynfe_xml2dict/__init__.py
pynfe_xml2dict/cte/__init__.py
pynfe_xml2dict/cte/index.py
pynfe_xml2dict/nfce/__init__.py
pynfe_xml2dict/nfe/__init__.py
pynfe_xml2dict/nfe/__tag_dest__.py
pynfe_xml2dict/nfe/__tag_det__.py
pynfe_xml2dict/nfe/__tag_emit__.py
pynfe_xml2dict/nfe/__tag_ide__.py
pynfe_xml2dict/nfe/__tag_total__.py
pynfe_xml2dict/nfe/ler_nfe.py
pynfe_xml2dict/nfse/__init__.py
pynfe_xml2dict/nfse/index.py
pynfe_xml2dict/utils/__init__.py
pynfe_xml2dict/utils/functions.py
pynfe_xml2dict/utils/read_xml.py
pynfe_xml2dict-0.0.5.dist-info/METADATA
pynfe_xml2dict-0.0.5.dist-info/WHEEL
pynfe_xml2dict-0.0.5.dist-info/RECORD
