Metadata-Version: 2.1
Name: pynfe_xml2dict
Version: 0.0.5
Summary: Leitura de XML referente a notas fiscais NF-e, NFC-e e CT-e para dicionário
License: MIT
Keywords: python,nfe,xml
Author: ElderVivot
Author-email: eldervivot@gmail.com
Requires-Python: >=3.10,<4.0
Classifier: License :: OSI Approved :: MIT License
Classifier: Programming Language :: Python :: 3
Classifier: Programming Language :: Python :: 3.10
Classifier: Programming Language :: Python :: 3.11
Classifier: Programming Language :: Python :: 3.12
Requires-Dist: xmltodict (>=0.13.0,<0.14.0)
